LICENSE.txt
MANIFEST.in
README.md
setup.cfg
setup.py
seqpylogger/__init__.py
seqpylogger/config.py
seqpylogger/seqpylogger.py
seqpylogger/seqpyloggerhandler.py
seqpylogger/seqpyloggerqueuelistener.py
seqpylogger/seqsender.py
seqpylogger/serialization.py
seqpylogger/utils.py
seqpylogger.egg-info/PKG-INFO
seqpylogger.egg-info/SOURCES.txt
seqpylogger.egg-info/dependency_links.txt
seqpylogger.egg-info/requires.txt
seqpylogger.egg-info/top_level.txt
tests/test_seqpyloggerhandler.py
tests/test_usage.py
tests/test_utils.py