Metadata-Version: 2.1
Name: seqpylogger
Version: 1.1.1
Summary: python loghandler for seq
Home-page: https://github.com/wearetriple/seqpylogger
Download-URL: https://pypi.io/packages/source/s/seqpylogger/seqpylogger-1.1.1.tar.gz
Author: Triple
Classifier: Development Status :: 5 - Production/Stable
Classifier: Intended Audience :: Developers
Classifier: Topic :: System :: Logging
Classifier: License :: OSI Approved :: Apache Software License
Classifier: Programming Language :: Python
Classifier: Programming Language :: Python :: 3
License-File: LICENSE.txt
